{"id":"269a774f-ad00-4470-b6a1-fa564243e029","trainingStatus":"DONE","name":"mnt-pk","description":null,"trainingTime":"2025-05-31T06:43:48.974106Z","usage":{"totalDatapoints":-1,"totalComputeTime":null,"totalCredits":22.034426399999997,"totalVirtualCPUTime":38188.0,"totalVirtualGPUTime":2055.0,"noOfSyntheticDatasets":null,"noOfLikes":0},"metadata":{"creatorId":"b428ca24-9a34-4dea-b139-107fe7aa9b80","creatorName":"mostar","createdAt":"2025-05-31T06:02:58.073953Z","ownerId":"b428ca24-9a34-4dea-b139-107fe7aa9b80","ownerName":"mostar","ownerType":"USER","ownerImage":"https://app.mostly.ai/api/v2/users/b428ca24-9a34-4dea-b139-107fe7aa9b80/logo/logo.png","visibility":"PRIVATE","currentUserPermissionLevel":"ADMIN","currentUserLikeStatus":false,"shortLivedFileToken":"xc7o7HTmlH0tPy84d1BAeRunMUx9k1BxnGfJViq2GNrEQmQWMmAb20kDxo3ULWtb3oEZbJiN0ZKbaQi-QNzPSVB3x7HCIYC8-nuBarIQvctkATyakvecdvd8E50EE-di"},"accuracy":0.913,"tables":[{"id":"9fe32dd2-c680-4b6f-b721-d516182990f9","name":"part.000000.000000","sourceConnectorId":"32158613-d5db-4235-868e-ca98af076f46","location":"mostly-production-mostly-s3-bucket-mostly-app/connectors/32158613-d5db-4235-868e-ca98af076f46/part.000000.000000/part.000000.000000.parquet","primaryKey":null,"columns":[{"id":"f8e22fc6-6ed9-4a14-9e21-bda2c14fcde6","name":"destination_country","modelEncodingType":"TABULAR_CATEGORICAL","included":true,"valueRange":{"min":null,"max":null,"values":["\u0001_RARE_","Burundi","Central Africa Republic","Chad","Comoros","Cote d'lvoire","DR Congo","Eritrea","Ethiopia","Guinea","Madagascar","Mauritius","Rwanda","Rwanda ","Sao Tome","Sierra Leone","Sudan","Tanzania","Uganda","Zambia","Zimbabwe"],"has_null":false}},{"id":"4d5eb671-fa3d-4126-ab6b-c62bd854704e","name":"carrier","modelEncodingType":"TABULAR_CATEGORICAL","included":true,"valueRange":{"min":null,"max":null,"values":["\u0001_RARE_","DHL Express","Freight In Time","Freight In time","Freight in time","KQ:Direct charter","Kenya Airways","Kuehne Nagel","Nonso","Scan Global","Siginon Logistics","UNHAS "],"has_null":false}},{"id":"4c2f328e-43e0-4ffd-ab51-d01a8ab9d97e","name":"weight_kg","modelEncodingType":"TABULAR_NUMERIC_BINNED","included":true,"valueRange":{"min":"8.0","max":"65536.0","values":null,"has_null":false}},{"id":"8b3342bc-05cc-4a99-aad2-b78c222cc855","name":"volume_cbm","modelEncodingType":"TABULAR_NUMERIC_BINNED","included":true,"valueRange":{"min":"0.0","max":"256.0","values":null,"has_null":false}},{"id":"036686e0-6453-4b6d-aacb-2fb24137163a","name":"signed_or_date","modelEncodingType":"TABULAR_DATETIME","included":true,"valueRange":{"min":null,"max":null,"values":null,"has_null":false}},{"id":"7fd7c46c-dbe4-4279-aa53-9883af654965","name":"request_reference_n°","modelEncodingType":"LANGUAGE_TEXT","included":true,"valueRange":{"min":null,"max":null,"values":null,"has_null":false}},{"id":"a5ecc6f3-540e-4257-b86d-2c9142ad28d7","name":"greenlight_date","modelEncodingType":"TABULAR_DATETIME","included":true,"valueRange":{"min":null,"max":null,"values":null,"has_null":false}},{"id":"617f9309-c849-43ca-9ee0-f20c7fb86de6","name":"dispatch_date","modelEncodingType":"TABULAR_DATETIME","included":true,"valueRange":{"min":null,"max":null,"values":null,"has_null":false}},{"id":"2483dc63-8990-4322-8171-9a5256a8a1f3","name":"request_date","modelEncodingType":"TABULAR_DATETIME","included":true,"valueRange":{"min":null,"max":null,"values":null,"has_null":false}},{"id":"c7ddbbd9-b2a1-456d-8404-ea4f8894f9be","name":"route","modelEncodingType":"TABULAR_CATEGORICAL","included":true,"valueRange":{"min":null,"max":null,"values":["Kenya-Burundi","Kenya-Central Africa Republic","Kenya-Chad","Kenya-Comoros","Kenya-Cote d'lvoire","Kenya-DR Congo","Kenya-Eritrea","Kenya-Ethiopia","Kenya-Guinea","Kenya-Madagascar","Kenya-Mauritius","Kenya-Rwanda","Kenya-Rwanda ","Kenya-Sao Tome","Kenya-Sierra Leone","Kenya-Sudan","Kenya-Tanzania","Kenya-Uganda","Kenya-Zambia","Kenya-Zimbabwe","Kenya-_RARE_"],"has_null":false}},{"id":"78188d7a-856f-448e-a17f-ed556f024284","name":"days_to_dispatch","modelEncodingType":"TABULAR_NUMERIC_DIGIT","included":true,"valueRange":{"min":null,"max":null,"values":null,"has_null":false}},{"id":"97251d19-dd85-49b8-a2f8-46ac572cd0bd","name":"days_to_greenlight","modelEncodingType":"TABULAR_NUMERIC_DIGIT","included":true,"valueRange":{"min":null,"max":null,"values":null,"has_null":false}},{"id":"91a8955c-89da-449c-a8ed-638218167ed1","name":"vol_weight_ratio","modelEncodingType":"TABULAR_NUMERIC_BINNED","included":true,"valueRange":{"min":"0.0","max":"8.0","values":null,"has_null":false}},{"id":"5837a702-9d05-4f0c-a824-c2bc8bc1abcb","name":"carrier_dest","modelEncodingType":"TABULAR_CATEGORICAL","included":true,"valueRange":{"min":null,"max":null,"values":["DHL Express-Central Africa Republic","DHL Express-Chad","DHL Express-Comoros","DHL Express-Cote d'lvoire","DHL Express-DR Congo","DHL Express-Eritrea","DHL Express-Ethiopia","DHL Express-Guinea","DHL Express-Madagascar","DHL Express-Mauritius","DHL Express-Rwanda","DHL Express-Rwanda ","DHL Express-Sao Tome","DHL Express-Sierra Leone","DHL Express-Sudan","DHL Express-Tanzania","DHL Express-Uganda","DHL Express-Zambia","DHL Express-Zimbabwe","DHL Express-_RARE_","Freight In Time-Burundi","Freight In Time-Central Africa Republic","Freight In Time-Chad","Freight In Time-Comoros","Freight In Time-Cote d'lvoire","Freight In Time-DR Congo","Freight In Time-Eritrea","Freight In Time-Ethiopia","Freight In Time-Guinea","Freight In Time-Sao Tome","Freight In Time-Sierra Leone","Freight In Time-Sudan","Freight In Time-Tanzania","Freight In Time-Uganda","Freight In Time-Zambia","Freight In Time-Zimbabwe","Freight In Time-_RARE_","Freight In time-Burundi","Freight In time-Central Africa Republic","Freight In time-Chad","Freight In time-Comoros","Freight In time-Cote d'lvoire","Freight In time-DR Congo","Freight In time-Eritrea","Freight In time-Ethiopia","Freight In time-Guinea","Freight In time-Madagascar","Freight In time-Mauritius","Freight In time-Rwanda","Freight In time-Rwanda ","Freight In time-Sao Tome","Freight In time-Sierra Leone","Freight In time-Sudan","Freight In time-Tanzania","Freight In time-Uganda","Freight In time-Zambia","Freight In time-Zimbabwe","Freight In time-_RARE_","Freight in time-Burundi","Freight in time-Comoros","Freight in time-DR Congo","Freight in time-Eritrea","Freight in time-Ethiopia","Freight in time-Guinea","Freight in time-Madagascar","Freight in time-Mauritius","Freight in time-Rwanda","Freight in time-Rwanda ","Freight in time-Sao Tome","Freight in time-Sierra Leone","Freight in time-Tanzania","Freight in time-Uganda","Freight in time-Zambia","Freight in time-Zimbabwe","Freight in time-_RARE_","KQ:Direct charter-Burundi","KQ:Direct charter-Central Africa Republic","KQ:Direct charter-Chad","KQ:Direct charter-Comoros","KQ:Direct charter-Cote d'lvoire","KQ:Direct charter-DR Congo","KQ:Direct charter-Ethiopia","KQ:Direct charter-Guinea","KQ:Direct charter-Madagascar","KQ:Direct charter-Mauritius","KQ:Direct charter-Rwanda","KQ:Direct charter-Rwanda ","KQ:Direct charter-Sao Tome","KQ:Direct charter-Sierra Leone","KQ:Direct charter-Sudan","KQ:Direct charter-Tanzania","KQ:Direct charter-Uganda","KQ:Direct charter-Zambia","KQ:Direct charter-Zimbabwe","KQ:Direct charter-_RARE_","Kenya Airways-Burundi","Kenya Airways-Central Africa Republic","Kenya Airways-Chad","Kenya Airways-Comoros","Kenya Airways-Cote d'lvoire","Kenya Airways-DR Congo","Kenya Airways-Eritrea","Kenya Airways-Ethiopia","Kenya Airways-Guinea","Kenya Airways-Madagascar","Kenya Airways-Rwanda","Kenya Airways-Rwanda ","Kenya Airways-Sao Tome","Kenya Airways-Sierra Leone","Kenya Airways-Sudan","Kenya Airways-Tanzania","Kenya Airways-Uganda","Kenya Airways-Zambia","Kenya Airways-Zimbabwe","Kenya Airways-_RARE_","Kuehne Nagel-Burundi","Kuehne Nagel-Central Africa Republic","Kuehne Nagel-Chad","Kuehne Nagel-Comoros","Kuehne Nagel-Cote d'lvoire","Kuehne Nagel-DR Congo","Kuehne Nagel-Eritrea","Kuehne Nagel-Ethiopia","Kuehne Nagel-Guinea","Kuehne Nagel-Madagascar","Kuehne Nagel-Mauritius","Kuehne Nagel-Rwanda","Kuehne Nagel-Rwanda ","Kuehne Nagel-Sao Tome","Kuehne Nagel-Sierra Leone","Kuehne Nagel-Sudan","Kuehne Nagel-Tanzania","Kuehne Nagel-Uganda","Kuehne Nagel-Zambia","Kuehne Nagel-Zimbabwe","Kuehne Nagel-_RARE_","Nonso-Chad","Nonso-Comoros","Nonso-Cote d'lvoire","Nonso-DR Congo","Nonso-Eritrea","Nonso-Mauritius","Nonso-Rwanda ","Nonso-Sao Tome","Nonso-Sierra Leone","Nonso-Sudan","Nonso-Tanzania","Nonso-Uganda","Nonso-Zimbabwe","Scan Global-Burundi","Scan Global-Central Africa Republic","Scan Global-Chad","Scan Global-DR Congo","Scan Global-Eritrea","Scan Global-Guinea","Scan Global-Madagascar","Scan Global-Rwanda ","Scan Global-Sao Tome","Scan Global-Sierra Leone","Scan Global-Tanzania","Scan Global-Uganda","Scan Global-Zimbabwe","Scan Global-_RARE_","Siginon Logistics-Burundi","Siginon Logistics-Central Africa Republic","Siginon Logistics-Chad","Siginon Logistics-Comoros","Siginon Logistics-Cote d'lvoire","Siginon Logistics-DR Congo","Siginon Logistics-Eritrea","Siginon Logistics-Ethiopia","Siginon Logistics-Guinea","Siginon Logistics-Madagascar","Siginon Logistics-Mauritius","Siginon Logistics-Rwanda","Siginon Logistics-Rwanda ","Siginon Logistics-Sao Tome","Siginon Logistics-Sierra Leone","Siginon Logistics-Sudan","Siginon Logistics-Tanzania","Siginon Logistics-Uganda","Siginon Logistics-Zambia","Siginon Logistics-Zimbabwe","Siginon Logistics-_RARE_","UNHAS -Burundi","UNHAS -Chad","UNHAS -Comoros","UNHAS -Ethiopia","UNHAS -Guinea","UNHAS -Madagascar","UNHAS -Mauritius","UNHAS -Rwanda","UNHAS -Rwanda ","UNHAS -Sao Tome","UNHAS -Sierra Leone","UNHAS -Sudan","UNHAS -Tanzania","UNHAS -Uganda","UNHAS -_RARE_","_RARE_-Burundi","_RARE_-Central Africa Republic","_RARE_-Chad","_RARE_-Comoros","_RARE_-DR Congo","_RARE_-Eritrea","_RARE_-Ethiopia","_RARE_-Madagascar","_RARE_-Rwanda","_RARE_-Rwanda ","_RARE_-Sao Tome","_RARE_-Sierra Leone","_RARE_-Sudan","_RARE_-Tanzania","_RARE_-Uganda","_RARE_-Zambia","_RARE_-Zimbabwe","_RARE_-_RARE_"],"has_null":false}}],"foreignKeys":null,"tabularModelMetrics":null,"languageModelMetrics":{"accuracy":{"overall":0.913,"univariate":0.959,"bivariate":0.868,"trivariate":null,"coherence":null,"overallMax":0.911,"univariateMax":0.954,"bivariateMax":0.867,"trivariateMax":null,"coherenceMax":null},"distances":{"imsTraining":0.0,"imsHoldout":0.0,"imsTrnHol":0.0,"dcrTraining":0.058,"dcrHoldout":0.087,"dcrTrnHol":0.132,"dcrShare":1.0,"nndrTraining":0.396,"nndrHoldout":0.581,"nndrTrnHol":0.315},"similarity":{"cosineSimilarityTrainingSynthetic":0.97082,"cosineSimilarityTrainingHoldout":0.99889,"discriminatorAUCTrainingSynthetic":1.0,"discriminatorAUCTrainingHoldout":0.534}},"tabularModelConfiguration":{"model":"MOSTLY_AI/Large","maxSampleSize":270894,"batchSize":1024,"gradientAccumulationSteps":1024,"maxTrainingTime":30.0,"maxEpochs":10000.0,"maxSequenceWindow":100,"enableFlexibleGeneration":true,"valueProtection":true,"rareCategoryReplacementMethod":"CONSTANT","differentialPrivacy":{"maxEpsilon":10.0,"delta":1.0E-5,"noiseMultiplier":1.5,"maxGradNorm":1.0,"valueProtectionEpsilon":1.0},"compute":"72ead877-b181-432b-876f-6a1116dcde11","enableModelReport":true},"languageModelConfiguration":{"model":"MOSTLY_AI/LSTMFromScratch-3m","maxSampleSize":270894,"batchSize":null,"gradientAccumulationSteps":null,"maxTrainingTime":10.0,"maxEpochs":100.0,"maxSequenceWindow":null,"enableFlexibleGeneration":true,"valueProtection":true,"rareCategoryReplacementMethod":"CONSTANT","differentialPrivacy":null,"compute":"d2dc8ce3-2861-4bea-95c2-99c01a2ed084","enableModelReport":true},"totalRows":270894}],"randomState":null}